{"cameraMode":{"drawMode":0,"name":"Shaded","section":"Shading Mode"},"sceneLighting":false,"audioPlay":false,"sceneViewState":{"m_AlwaysRefresh":false,"showFog":true,"showSkybox":false,"showFlares":true,"showImageEffects":true,"showParticleSystems":true,"showVisualEffectGraphs":true,"m_FxEnabled":true},"in2DMode":false,"pivot":{"x":-2.5264883041381838,"y":1.0873675346374512,"z":-0.9096646308898926},"rotation":{"x":0.2761302590370178,"y":0.2788170874118805,"z":-0.0840587168931961,"w":0.9159362316131592},"size":1.866565227508545,"orthographic":false}